Workbook

Sheet Assumptions
A1: INNOVA — BOTTOM-UP SCOPE, EFFORT & BUDGET MODEL
A2: Konekti INTERNAL · Full scope (5 work packages) · Effort priced at day-rate; calendar modelled separately. Rev 4 — self-hosted Airbyte connectors, license €7,500/mo confirmed.
A4: 1 · PRICING & EFFORT DRIVERS (blue = inputs you change)
A6: Blended day rate (€/day) | B6: 1100 | E6: Adam's stated average across roles. Used to price ALL effort.
A7: Working days per week | B7: 5 | E7: For converting weeks <-> days.
A8: Day-rate sensitivity — low | B8: 1000 | E8: Lower price bound.
A9: Day-rate sensitivity — high | B9: 1250 | E9: Upper price bound.
A11: 2 · CONTINGENCY ON EFFORT (layered — applied to man-days, not calendar)
A13: Base contingency (all packages) | B13: 0.15 | E13: Standard estimation buffer on every WP. Covers normal underestimation.
A14: Risk uplift — high-uncertainty WPs | B14: 0.25 | E14: EXTRA, applied only to flagged WPs (WP3 attribution/identity, WP4 finance source, custom CDK builds).
A15: Client-responsiveness rework premium | B15: 0.08 | E15: Effort added by context-switching/cold-restart IF client is slow. 0% if highly responsive.
A17: 3 · CALENDAR DRIVERS (separate from cost — drive elapsed time only)
A19: Konekti delivery capacity (people on it) | B19: 1.5 | E19: Avg FTE actively delivering (analyst + dev capacity blended). Drives how fast effort burns down.
A20: Flow efficiency — fast/responsive client | B20: 0.65 | E20: % of calendar that is productive work. High = compressed timeline (CEO 'fast ~6mo').
A21: Flow efficiency — realistic | B21: 0.5 | E21: Normal back-and-forth (CEO 'realistic ~9mo').
A22: Flow efficiency — slow/unresponsive client | B22: 0.35 | E22: Waiting on access, answers, approvals (CEO 'up to ~12mo').
A24: 4 · COMMERCIAL (recurring)
A26: Konekti license €/month (5 seats) | B26: 7500 | E26: CONFIRMED monthly. Annualised on Scenarios tab.
A27: License months in year 1 | B27: 12 | E27: Set lower if licence starts mid-project.
A29: KEY MODELLING NOTES
A30: • EFFORT vs CALENDAR are decoupled. Effort (man-days) sets COST and never changes with client speed (except the small rework premium). CALENDAR (elapsed months) is a separate output driven by capacity + flow efficiency — this is the 6/9/12-month spread.
A31: • Connectors are SELF-HOSTED Airbyte + custom CDK builds. No monthly connector subscription. The work is one-off BUILD EFFORT, already inside WP effort. Only ongoing recurring cost is the Konekti license + LLM usage.
A32: • LLM API usage (OpenAI/Anthropic/Gemini, client-cloud-hosted) is a pass-through, still being defined. NOT in totals.

Sheet Effort Build-Up
A1: EFFORT BUILD-UP — man-days by work package (the cost foundation)
A2: Spine = CTO-agreed connector time (4 wks build + 2 wks setup, self-hosted Airbyte) + Adam's modelling/analytics weeks, decomposed across the 5 WPs. 'High-risk?' flags which WPs get the extra risk uplift.
A4: Work package / activity | B4: Layer | C4: Dev days | D4: Analyst days | E4: Base days | F4: High-risk? | G4: Risk days | H4: Cost (base+cont.) | I4: Notes
A5: Redshift warehouse + dbt foundation | B5: 1 | C5: 10 | D5: 0 | E5: =C5+D5 -> 10 | F5: — | G5: =IF(F5="Yes",E5*Assumptions!$B$14,0) -> 0 | H5: =(E5*(1+Assumptions!$B$13)+G5)*Assumptions!$B$6 -> 12650 | I5: CTO-agreed: 2 wks. Raw/staging/mart, dbt init, self-hosted Airbyte infra stood up.
A6: Connector builds — existing Airbyte sources | B6: 1 | C6: 10 | D6: 0 | E6: =C6+D6 -> 10 | F6: — | G6: =IF(F6="Yes",E6*Assumptions!$B$14,0) -> 0 | H6: =(E6*(1+Assumptions!$B$13)+G6)*Assumptions!$B$6 -> 12650 | I6: ~half the 10 sources exist in Airbyte; fast config. Part of CTO 4-wk connector estimate.
A7: Connector builds — custom CDK sources | B7: 1 | C7: 10 | D7: 0 | E7: =C7+D7 -> 10 | F7: Yes | G7: =IF(F7="Yes",E7*Assumptions!$B$14,0) -> 2.5 | H7: =(E7*(1+Assumptions!$B$13)+G7)*Assumptions!$B$6 -> 15400 | I7: Custom CDK for sources not in Airbyte (e.g. Eloqua activity, Dynamics audit, internal dashboard). Higher uncertainty.
A8: WP1 — Channel efficiency (CPL, CPA) | B8: 2-3 | C8: 3 | D8: 6 | E8: =C8+D8 -> 9 | F8: — | G8: =IF(F8="Yes",E8*Assumptions!$B$14,0) -> 0 | H8: =(E8*(1+Assumptions!$B$13)+G8)*Assumptions!$B$6 -> 11385 | I8: Ad platforms + GA4 + Search Console + CRM lead counts. Cost per lead / per action by channel. FASTEST metric to value. (CPS needs deal join -> WP2.)
A9: WP2 — Acquisition economics (CPS, CAC by source) | B9: 2-3 | C9: 2 | D9: 6 | E9: =C9+D9 -> 8 | F9: — | G9: =IF(F9="Yes",E9*Assumptions!$B$14,0) -> 0 | H9: =(E9*(1+Assumptions!$B$13)+G9)*Assumptions!$B$6 -> 10120 | I9: Adds CRM pipeline + lead-source + closed-deal join. Cost per SALE and CAC by source. 'Sale' = closed deal/subscription in Dynamics, not an ad event.
A10: WP3 — Click-to-revenue attribution | B10: 2-3 | C10: 12 | D10: 8 | E10: =C10+D10 -> 20 | F10: Yes | G10: =IF(F10="Yes",E10*Assumptions!$B$14,0) -> 5 | H10: =(E10*(1+Assumptions!$B$13)+G10)*Assumptions!$B$6 -> 30800 | I10: Identity stitching click->lead->deal. 'Which channel drives REVENUE.' First/last/data-driven models. The hard one.
A11: WP4 — Unit economics (LTV, LTV:CAC) | B11: 2-3 | C11: 4 | D11: 5 | E11: =C11+D11 -> 9 | F11: Yes | G11: =IF(F11="Yes",E11*Assumptions!$B$14,0) -> 2.25 | H11: =(E11*(1+Assumptions!$B$13)+G11)*Assumptions!$B$6 -> 13860 | I11: Adds finance/orders realised revenue, joined to accounts. Real LTV and LTV:CAC by source.
A12: Analytics & AI — modelling that fuels reports | B12: 3 | C12: 0 | D12: 8 | E12: =C12+D12 -> 8 | F12: — | G12: =IF(F12="Yes",E12*Assumptions!$B$14,0) -> 0 | H12: =(E12*(1+Assumptions!$B$13)+G12)*Assumptions!$B$6 -> 10120 | I12: ANALYST side: anomaly logic, forecast models, the analytics behind alerts/reports, NL Q&A model in Konekti.
A13: Automation & downstream wiring (Konekti + n8n + Teams) | B13: 3 | C13: 15 | D13: 0 | E13: =C13+D13 -> 15 | F13: — | G13: =IF(F13="Yes",E13*Assumptions!$B$14,0) -> 0 | H13: =(E13*(1+Assumptions!$B$13)+G13)*Assumptions!$B$6 -> 18975 | I13: DEV side: wire Konekti outputs into n8n workflows, push automated reports to Teams, build alert plumbing & integrations. Min. 15 days; runs in parallel across the project.
A14: Handover: docs, training, SLA | B14: 4 | C14: 2 | D14: 5 | E14: =C14+D14 -> 7 | F14: — | G14: =IF(F14="Yes",E14*Assumptions!$B$14,0) -> 0 | H14: =(E14*(1+Assumptions!$B$13)+G14)*Assumptions!$B$6 -> 8855 | I14: Lightweight.
A15: TOTAL — base effort | C15: =SUM(C5:C14) -> 68 | D15: =SUM(D5:D14) -> 38 | E15: =SUM(E5:E14) -> 106 | G15: =SUM(G5:G14) -> 9.75 | H15: =SUM(H5:H14) -> 144815
A16: Loaded effort incl. contingency (days) | E16: ='Effort Build-Up'!$E$15*(1+Assumptions!$B$13)+'Effort Build-Up'!$G$15 -> 131.65 | H16: =E16*Assumptions!$B$6 -> 144815 | I16: Excl. client-responsiveness rework premium (added in Scenarios).

Sheet Scenarios
A1: SCENARIOS — cost (effort) and calendar (time) shown SEPARATELY
A3: A · COST — driven by EFFORT (changes little with client speed)
A4: Scenario | B4: Effort (days) | C4: Rework premium | D4: Total cost (services) | F4: Driver
A5: Responsive client | B5: ='Effort Build-Up'!$E$16*(1+Assumptions!$B$15*0) -> 131.65 | C5: ='Effort Build-Up'!$E$16*Assumptions!$B$15*0*Assumptions!$B$6 -> 0 | D5: =B5*Assumptions!$B$6 -> 144815 | F5: No restarts; rework premium not applied
A6: Realistic | B6: ='Effort Build-Up'!$E$16*(1+Assumptions!$B$15*0.5) -> 136.916 | C6: ='Effort Build-Up'!$E$16*Assumptions!$B$15*0.5*Assumptions!$B$6 -> 5792.6 | D6: =B6*Assumptions!$B$6 -> 150607.6 | F6: Half the rework premium — normal friction
A7: Slow client | B7: ='Effort Build-Up'!$E$16*(1+Assumptions!$B$15*1) -> 142.182 | C7: ='Effort Build-Up'!$E$16*Assumptions!$B$15*1*Assumptions!$B$6 -> 11585.2 | D7: =B7*Assumptions!$B$6 -> 156400.2 | F7: Full rework premium — cold restarts add effort
A9: B · CALENDAR — driven by client RESPONSIVENESS (does NOT change the price)
A10: Scenario | B10: Effort (days) | C10: Flow efficiency | D10: Elapsed months | F10: CEO's read
A11: Fast / responsive | B11: =B5 -> 131.65 | C11: =Assumptions!$B$20 -> 0.65 | D11: =B11/Assumptions!$B$19/C11/21.7 -> 6.2223798 | F11: ~6 months ('fast' per CEO)
A12: Realistic | B12: =B6 -> 136.916 | C12: =Assumptions!$B$21 -> 0.5 | D12: =B12/Assumptions!$B$19/C12/21.7 -> 8.4126575 | F12: ~9 months ('realistic' per CEO)
A13: Slow / unresponsive | B13: =B7 -> 142.182 | C13: =Assumptions!$B$22 -> 0.35 | D13: =B13/Assumptions!$B$19/C13/21.7 -> 12.480316 | F13: up to ~12 months per CEO
A15: C · YEAR-ONE ALL-IN (services + first-year Konekti license)
A16: Scenario | B16: Services | C16: License (yr 1) | D16: Year-1 total | F16: Note
A17: Low (responsive) | B17: =D5 -> 144815 | C17: =(Assumptions!$B$26*Assumptions!$B$27) -> 90000 | D17: =B17+C17 -> 234815 | F17: Floor; clean & fast
A18: Realistic | B18: =D6 -> 150607.6 | C18: =(Assumptions!$B$26*Assumptions!$B$27) -> 90000 | D18: =B18+C18 -> 240607.6 | F18: Plan around this
A19: High (slow + risk realised) | B19: =D7 -> 156400.2 | C19: =(Assumptions!$B$26*Assumptions!$B$27) -> 90000 | D19: =B19+C19 -> 246400.2 | F19: Slow client; risk WPs overrun
A21: + LLM API usage: TBD pass-through, NOT included. + Year-2 onward: license €90k/yr recurring.
A23: HOW TO USE THIS: the COST (block A) is what you quote and what it costs you to deliver — it barely moves with client speed. The CALENDAR (block B) is the timeline COMMITMENT — that's what flexes 6->9->12 months on client responsiveness. Quote a fixed price band off block A; commit to a timeline RANGE off block B, with a clause that elapsed time assumes agreed client response SLAs (access, answers, approvals).

Sheet WP1 First Quote
A1: WP1 — FIRST-QUOTE PACKAGE (lead with this)
A3: Quote ONE package tight first. WP1 = Channel efficiency: CPL / CPA by channel — the fastest of Andrzej's named metrics to deliver. NOTE: this assumes the FULL foundation is built first — full Redshift config, ALL connectors, then dbt on top — because the data model and later WPs all depend on it. So WP1's price carries the whole foundation.
A5: Component | B5: Days | C5: Cost | D5: Note
A6: Full Redshift configuration | B6: 10 | C6: =B6*Assumptions!$B$6 -> 11000 | D6: Complete warehouse setup: raw/staging/mart scaffolding.
A7: All connectors built (existing Airbyte + custom CDK) | B7: 30 | C7: =B7*Assumptions!$B$6 -> 33000 | D7: Every source landed — existing config + custom CDK builds. The full Layer-1 effort up front.
A8: dbt + transformation layer on landed data | B8: 10 | C8: =B8*Assumptions!$B$6 -> 11000 | D8: Built once all connectors are landing; the modelling backbone.
A9: Model channel efficiency (CPL/CPA) + NL Q&A | B9: 6 | C9: =B9*Assumptions!$B$6 -> 6600 | D9: Analyst side: the WP1 metric model + conversational layer.
A10: Lightweight handover for WP1 | B10: 3 | C10: =B10*Assumptions!$B$6 -> 3300 | D10: Docs + walkthrough for first package.
A11: WP1 base | B11: =SUM(B6:B10) -> 59 | C11: =SUM(C6:C10) -> 64900
A12: WP1 with 15% contingency | B12: =B11*(1+Assumptions!$B$13) -> 67.85 | C12: =C11*(1+Assumptions!$B$13) -> 74635 | D12: The narrow first-quote number.
A14: Sequence the rest (WP2->WP4 + analytics layer) after WP1 lands and the tech answers tighten the risk WPs.

Sheet WP Map (metrics)
A1: WORK PACKAGES ANCHORED TO ANDRZEJ'S METRICS
A2: Each WP = a metric Andrzej named + the question it answers + the data it needs. Ordered fastest-metric-to-value. End-to-end view is built iteratively: every WP adds the next layer of the click->lead->deal->revenue funnel.
A4: Work package | B4: Metric(s) answered | C4: Andrzej's question | D4: Data needed | E4: Order
A5: Foundation | B5: (enabling) | C5: Stand up the warehouse so anything can land | D5: Redshift + dbt + self-hosted Airbyte | E5: 0 — first
A6: WP1 Channel efficiency | B6: CPL, CPA | C6: What does each channel cost per lead / per action? | D6: Ad platforms, GA4, Search Console, CRM lead counts | E6: 1 — fastest value
A7: WP2 Acquisition economics | B7: CPS, CAC by source | C7: Cost per SALE, and which sources produce DEALS not just leads? | D7: + CRM pipeline, lead-source & closed-deal join | E7: 2
A8: WP3 Click-to-revenue attribution | B8: Channel->revenue; first/last/data-driven | C8: Which channel actually drives REVENUE? Under which attribution model? | D8: + identity stitching click->lead->deal (UTM/click-ID) | E8: 3 — hardest
A9: WP4 Unit economics | B9: LTV, LTV:CAC | C9: What is real LTV and LTV:CAC per source? | D9: + finance/orders realised revenue, joined to accounts | E9: 4 — deepest data
A10: Analytics & AI layer | B10: All, conversational | C10: Alerts, weekly Teams reports, forecasting, ask-in-plain-language | D10: Full model (cross-cutting) | E10: Throughout
A11: Automation & downstream wiring | B11: (delivery) | C11: Push reports to Teams, n8n workflows, alert plumbing | D11: Konekti + n8n + Teams integration (dev) | E11: Throughout
A13: WHY THIS ORDER: the metrics have a natural dependency chain that also matches data-source readiness. CPL/CPA need only spend + lead counts (fast). CAC adds won-deal linkage. Channel->revenue needs identity resolution (hard). LTV:CAC needs realised revenue (deepest). So sequencing by fastest-metric-to-value ALSO builds the end-to-end funnel in the only order the data allows — no conflict between 'quick wins' and 'full picture'.

Sheet Parallel Workflow
A1: PARALLEL DELIVERY — dev lands a source, Konekti models it, dev flips to next
A2: The handoff: source connected -> landed structure in Redshift (dev) -> objects/activities modelled in Konekti (Adam) -> insights/reports/automations out. As soon as one source lands, Adam models while dev moves to the next. Calendar shown realistic (~9mo); compresses with a responsive client.
A4: Stream | B4: M1 | C4: M2 | D4: M3 | E4: M4 | F4: M5 | G4: M6 | H4: M7 | I4: M8 | J4: M9
A5: Foundation (Redshift/dbt/Airbyte)
A6: DEV: land WP1 sources
A7: ANALYST: model WP1 (CPL/CPA)
A8: DEV: land WP2 sources
A9: ANALYST: model WP2 (CPS/CAC)
A10: DEV: land WP3 sources + identity
A11: ANALYST: model WP3 (attribution)
A12: DEV: land WP4 finance source
A13: ANALYST: model WP4 (LTV:CAC)
A14: Analytics/AI: alerts, Teams, forecast, Q&A
A15: Handover, docs, training, SLA
A17: Legend: | B17: Dev | C17: Analyst | D17: Analytics
A19: First usable metric (WP1 CPL/CPA) lands ~M2-M3, not at the end. Each later WP delivers its metric as its data lands, so Andrzej sees value continuously while the end-to-end model fills in.
